{"id":193282,"name":"にゃんこデイズ","name_cn":"猫咪日常","type":"动画","image":"f0/6e/193282_Ca1UE.jpg","link":"https://bgm.tv/subject/193282","eps":12,"collection":{"on_hold":95,"dropped":95,"wish":305,"collect":3300,"doing":109},"date":"2017-01-08","summary":"故事讲述了怕生的女孩小长井友子和她饲养的3只猫咪的日常。而这3只猫分别是撒娇高手的“玛”、淡定王“罗”、爱哭鬼“西”，她们有着人的形态，有猫耳和尾巴，会说人类语言。","rating":{"rank":5666,"total":1880,"count":{"1":2,"2":9,"3":16,"4":44,"5":236,"6":782,"7":592,"8":152,"9":16,"10":31},"score":6.3},"updated_at":"2022-12-23T02:42:54+08:00"}