{"id":227721,"name":"僕の彼女がマジメ過ぎる処女ビッチな件 OAD","name_cn":"关于我女友是个一本正经的碧池这件事 OAD","type":"动画","image":"b6/79/227721_DRFJ6.jpg","link":"https://bgm.tv/subject/227721","eps":1,"collection":{"on_hold":38,"dropped":28,"wish":199,"collect":883,"doing":30},"date":"2018-05-26","summary":"OAD限定の完全オリジナルエピソード!「もし篠崎と秋穂がセックスしないと出れない部屋に閉じ込められたら」と「エキサイト王様ゲーム」を収録。TVより過激なボイスと演出に、全裸待機待ったなし!?","rating":{"rank":7413,"total":419,"count":{"1":4,"2":5,"3":13,"4":31,"5":117,"6":156,"7":62,"8":21,"9":2,"10":8},"score":5.7},"updated_at":"2022-12-23T03:32:41+08:00"}